Metadata-Version: 1.0
Name: pyopendsix
Version: 0.0.4
Summary: Restful Python API based on OpenD6
Home-page: https://gitlab.com/HexGearInc/pyopendsix
Author: Lucas Ramage
Author-email: ramage.lucas@protonmail.com
License: MIT
Platform: UNKNOWN
